<?xml version="1.0"?>
<ArrayOfDroneCharge xmlns:xsi="http://www.w3.org/2001/XMLSchema-instance" xmlns:xsd="http://www.w3.org/2001/XMLSchema">
  <DroneCharge>
    <DroneId>123456</DroneId>
    <StationId>1234</StationId>
    <StartedChargeTime>2022-01-07T11:57:51.1830533+02:00</StartedChargeTime>
  </DroneCharge>
  <DroneCharge>
    <DroneId>123456</DroneId>
    <StationId>1234</StationId>
    <StartedChargeTime>2022-01-07T12:01:12.6403572+02:00</StartedChargeTime>
  </DroneCharge>
  <DroneCharge>
    <DroneId>123456</DroneId>
    <StationId>1234</StationId>
    <StartedChargeTime>2022-01-07T12:44:09.4536371+02:00</StartedChargeTime>
  </DroneCharge>
  <DroneCharge>
    <DroneId>123456</DroneId>
    <StationId>1234</StationId>
    <StartedChargeTime>2022-01-07T12:45:28.7474937+02:00</StartedChargeTime>
  </DroneCharge>
  <DroneCharge>
    <DroneId>234567</DroneId>
    <StationId>1234</StationId>
    <StartedChargeTime>2022-01-07T12:45:28.8043306+02:00</StartedChargeTime>
  </DroneCharge>
  <DroneCharge>
    <DroneId>123456</DroneId>
    <StationId>1234</StationId>
    <StartedChargeTime>2022-01-07T12:45:56.8293598+02:00</StartedChargeTime>
  </DroneCharge>
  <DroneCharge>
    <DroneId>123456</DroneId>
    <StationId>1234</StationId>
    <StartedChargeTime>2022-01-07T12:51:23.3840201+02:00</StartedChargeTime>
  </DroneCharge>
  <DroneCharge>
    <DroneId>123456</DroneId>
    <StationId>1234</StationId>
    <StartedChargeTime>2022-01-07T12:53:09.5076587+02:00</StartedChargeTime>
  </DroneCharge>
  <DroneCharge>
    <DroneId>123456</DroneId>
    <StationId>1234</StationId>
    <StartedChargeTime>2022-01-07T12:54:33.1554796+02:00</StartedChargeTime>
  </DroneCharge>
  <DroneCharge>
    <DroneId>123456</DroneId>
    <StationId>1234</StationId>
    <StartedChargeTime>2022-01-07T13:02:09.0238073+02:00</StartedChargeTime>
  </DroneCharge>
  <DroneCharge>
    <DroneId>123456</DroneId>
    <StationId>1234</StationId>
    <StartedChargeTime>2022-01-07T13:03:46.0292169+02:00</StartedChargeTime>
  </DroneCharge>
  <DroneCharge>
    <DroneId>234567</DroneId>
    <StationId>1234</StationId>
    <StartedChargeTime>2022-01-07T13:13:13.1721041+02:00</StartedChargeTime>
  </DroneCharge>
</ArrayOfDroneCharge>